ppinet/__init__.py
ppinet/clustering.py
ppinet/initial.py
ppinet/network_metrics.py
ppinet/ppinet.py
ppinet/sp.py
ppinet-0.1.0.dist-info/LICENSE
ppinet-0.1.0.dist-info/METADATA
ppinet-0.1.0.dist-info/WHEEL
ppinet-0.1.0.dist-info/entry_points.txt
ppinet-0.1.0.dist-info/top_level.txt
ppinet-0.1.0.dist-info/RECORD
