Metadata-Version: 2.1
Name: ppinet
Version: 0.1.0
Summary: A Python package for biological network generation and analysis.
Home-page: https://github.com/lmigueel/ppinet/
Author: Luca Miguel de Carvalho
Author-email: lucasmigueel@gmail.com
License: GNU General Public License v3.0
Keywords: bioinformatics,PPI network,shortest-path,stringdb
Platform: UNKNOWN
Classifier: Development Status :: 3 - Alpha
Classifier: Intended Audience :: Science/Research
Classifier: Natural Language :: English
Classifier: Topic :: Software Development :: Libraries
Classifier: Topic :: Scientific/Engineering :: Bio-Informatics
Classifier: License :: OSI Approved :: GNU General Public License (GPL)
Classifier: Programming Language :: Python :: 3
Requires-Python: >=3
Requires-Dist: matplotlib
Requires-Dist: numpy
Requires-Dist: pandas
Requires-Dist: networkx (>=2.5)
Requires-Dist: stringdb
Requires-Dist: python-louvain
Requires-Dist: scipy (>=1.6.1)
